tinygrad/__init__.py
tinygrad/device.py
tinygrad/dtype.py
tinygrad/gradient.py
tinygrad/helpers.py
tinygrad/py.typed
tinygrad/tensor.py
tinygrad/apps/llm.py
tinygrad/codegen/__init__.py
tinygrad/codegen/devectorizer.py
tinygrad/codegen/expander.py
tinygrad/codegen/gpudims.py
tinygrad/codegen/linearize.py
tinygrad/codegen/lowerer.py
tinygrad/codegen/quantize.py
tinygrad/codegen/opt/__init__.py
tinygrad/codegen/opt/heuristic.py
tinygrad/codegen/opt/kernel.py
tinygrad/codegen/opt/search.py
tinygrad/codegen/opt/swizzler.py
tinygrad/codegen/opt/tc.py
tinygrad/engine/__init__.py
tinygrad/engine/jit.py
tinygrad/engine/memory.py
tinygrad/engine/realize.py
tinygrad/engine/schedule.py
tinygrad/frontend/__init__.py
tinygrad/frontend/onnx.py
tinygrad/frontend/torch.py
tinygrad/nn/__init__.py
tinygrad/nn/datasets.py
tinygrad/nn/optim.py
tinygrad/nn/state.py
tinygrad/renderer/__init__.py
tinygrad/renderer/cstyle.py
tinygrad/renderer/llvmir.py
tinygrad/renderer/ptx.py
tinygrad/renderer/wgsl.py
tinygrad/runtime/__init__.py
tinygrad/runtime/ops_amd.py
tinygrad/runtime/ops_cpu.py
tinygrad/runtime/ops_cuda.py
tinygrad/runtime/ops_disk.py
tinygrad/runtime/ops_dsp.py
tinygrad/runtime/ops_gpu.py
tinygrad/runtime/ops_hip.py
tinygrad/runtime/ops_llvm.py
tinygrad/runtime/ops_metal.py
tinygrad/runtime/ops_npy.py
tinygrad/runtime/ops_null.py
tinygrad/runtime/ops_nv.py
tinygrad/runtime/ops_python.py
tinygrad/runtime/ops_qcom.py
tinygrad/runtime/ops_remote.py
tinygrad/runtime/ops_webgpu.py
tinygrad/runtime/autogen/adreno.py
tinygrad/runtime/autogen/amd_gpu.py
tinygrad/runtime/autogen/comgr.py
tinygrad/runtime/autogen/comgr_3.py
tinygrad/runtime/autogen/cuda.py
tinygrad/runtime/autogen/hip.py
tinygrad/runtime/autogen/hsa.py
tinygrad/runtime/autogen/ib.py
tinygrad/runtime/autogen/io_uring.py
tinygrad/runtime/autogen/kfd.py
tinygrad/runtime/autogen/kgsl.py
tinygrad/runtime/autogen/libc.py
tinygrad/runtime/autogen/libusb.py
tinygrad/runtime/autogen/llvm.py
tinygrad/runtime/autogen/nv_gpu.py
tinygrad-0.11.0.dist-info/licenses/LICENSE
tinygrad-0.11.0.dist-info/METADATA
tinygrad-0.11.0.dist-info/WHEEL
tinygrad-0.11.0.dist-info/top_level.txt
tinygrad-0.11.0.dist-info/RECORD
