Metadata-Version: 2.4
Name: tinygrad
Version: 0.11.0
Summary: You like pytorch? You like micrograd? You love tinygrad! <3
Author: George Hotz
License: MIT
Classifier: Programming Language :: Python :: 3
Classifier: License :: OSI Approved :: MIT License
Requires-Python: >=3.10
License-File: LICENSE
Provides-Extra: arm
Requires-Dist: unicorn; extra == "arm"
Provides-Extra: triton
Requires-Dist: triton-nightly>=2.1.0.dev20231014192330; extra == "triton"
Provides-Extra: linting
Requires-Dist: pylint; extra == "linting"
Requires-Dist: mypy==1.13.0; extra == "linting"
Requires-Dist: typing-extensions; extra == "linting"
Requires-Dist: pre-commit; extra == "linting"
Requires-Dist: ruff; extra == "linting"
Requires-Dist: numpy; extra == "linting"
Provides-Extra: testing-minimal
Requires-Dist: numpy; extra == "testing-minimal"
Requires-Dist: torch==2.7.1; extra == "testing-minimal"
Requires-Dist: pytest; extra == "testing-minimal"
Requires-Dist: pytest-xdist; extra == "testing-minimal"
Requires-Dist: hypothesis; extra == "testing-minimal"
Requires-Dist: z3-solver; extra == "testing-minimal"
Requires-Dist: ml_dtypes; extra == "testing-minimal"
Provides-Extra: testing-unit
Requires-Dist: numpy; extra == "testing-unit"
Requires-Dist: torch==2.7.1; extra == "testing-unit"
Requires-Dist: pytest; extra == "testing-unit"
Requires-Dist: pytest-xdist; extra == "testing-unit"
Requires-Dist: hypothesis; extra == "testing-unit"
Requires-Dist: z3-solver; extra == "testing-unit"
Requires-Dist: ml_dtypes; extra == "testing-unit"
Requires-Dist: tqdm; extra == "testing-unit"
Requires-Dist: safetensors; extra == "testing-unit"
Requires-Dist: tabulate; extra == "testing-unit"
Provides-Extra: testing
Requires-Dist: numpy; extra == "testing"
Requires-Dist: torch==2.7.1; extra == "testing"
Requires-Dist: pytest; extra == "testing"
Requires-Dist: pytest-xdist; extra == "testing"
Requires-Dist: hypothesis; extra == "testing"
Requires-Dist: z3-solver; extra == "testing"
Requires-Dist: ml_dtypes; extra == "testing"
Requires-Dist: pillow; extra == "testing"
Requires-Dist: onnx==1.18.0; extra == "testing"
Requires-Dist: onnx2torch; extra == "testing"
Requires-Dist: onnxruntime; extra == "testing"
Requires-Dist: opencv-python; extra == "testing"
Requires-Dist: tabulate; extra == "testing"
Requires-Dist: tqdm; extra == "testing"
Requires-Dist: safetensors; extra == "testing"
Requires-Dist: transformers; extra == "testing"
Requires-Dist: sentencepiece; extra == "testing"
Requires-Dist: tiktoken; extra == "testing"
Requires-Dist: blobfile; extra == "testing"
Requires-Dist: librosa; extra == "testing"
Requires-Dist: networkx; extra == "testing"
Requires-Dist: nibabel; extra == "testing"
Requires-Dist: bottle; extra == "testing"
Requires-Dist: ggml-python; extra == "testing"
Requires-Dist: capstone; extra == "testing"
Requires-Dist: pycocotools; extra == "testing"
Requires-Dist: boto3; extra == "testing"
Requires-Dist: pandas; extra == "testing"
Requires-Dist: influxdb3-python; extra == "testing"
Provides-Extra: docs
Requires-Dist: mkdocs; extra == "docs"
Requires-Dist: mkdocs-material; extra == "docs"
Requires-Dist: mkdocstrings[python]; extra == "docs"
Requires-Dist: markdown-callouts; extra == "docs"
Requires-Dist: markdown-exec[ansi]; extra == "docs"
Requires-Dist: black; extra == "docs"
Requires-Dist: numpy; extra == "docs"
Dynamic: author
Dynamic: classifier
Dynamic: description
Dynamic: description-content-type
Dynamic: license
Dynamic: license-file
Dynamic: provides-extra
Dynamic: requires-python
Dynamic: summary
